anbima_data/__init__.py
anbima_data/core.py
anbima_data/_internals/__init__.py
anbima_data/_internals/_utils.py
anbima_data-0.1.4.dist-info/licenses/LICENSE
anbima_data-0.1.4.dist-info/METADATA
anbima_data-0.1.4.dist-info/WHEEL
anbima_data-0.1.4.dist-info/top_level.txt
anbima_data-0.1.4.dist-info/RECORD
