Metadata-Version: 2.4
Name: anbima-data
Version: 0.1.4
Summary: Provides Python functions to retrieve public data from ANBIMA related to the Brazilian fixed income market.
Home-page: https://github.com/AlianeVdeC/anbima-data
Author: Aliane Vieira de Castro
Author-email: Aliane Vieira de Castro <sardineportfolio@protonmail.com>
License: MIT
Project-URL: Homepage, https://github.com/AlianeVdeC/anbima-data
Requires-Python: >=3.7
License-File: LICENSE
Requires-Dist: pandas
Requires-Dist: requests
Requires-Dist: plotly
Requires-Dist: beautifulsoup4
Dynamic: author
Dynamic: home-page
Dynamic: license-file
Dynamic: requires-python
